setup.py
crocodoc/__init__.py
crocodoc/document.py
crocodoc/download.py
crocodoc/session.py
crocodoc/version.py
crocodoc.egg-info/PKG-INFO
crocodoc.egg-info/SOURCES.txt
crocodoc.egg-info/dependency_links.txt
crocodoc.egg-info/not-zip-safe
crocodoc.egg-info/requires.txt
crocodoc.egg-info/top_level.txt